{
  "book": "job",
  "bookName": "Job",
  "testament": "OT",
  "chapter": 16,
  "totalChapters": 42,
  "verses": [
    {
      "n": 1,
      "t": "Then Job answered and said,"
    },
    {
      "n": 2,
      "t": "I have heard many such things: miserable comforters are you all."
    },
    {
      "n": 3,
      "t": "Shall vain words have an end? or what emboldens you that you answer?"
    },
    {
      "n": 4,
      "t": "I also could speak as you do: if your soul were in my soul’s stead, I could heap up words against you, and shake my head at you."
    },
    {
      "n": 5,
      "t": "But I would strengthen you with my mouth, and the moving of my lips should assuage your grief."
    },
    {
      "n": 6,
      "t": "Though I speak, my grief is not assuaged: and though I forbear, what am I eased?"
    },
    {
      "n": 7,
      "t": "But now he has made me weary: you have made desolate all my company."
    },
    {
      "n": 8,
      "t": "And you have filled me with wrinkles, which is a witness against me: and my leanness rising up in me bears witness to my face."
    },
    {
      "n": 9,
      "t": "He tears me in his wrath, who hates me: he gnashes on me with his teeth; my enemy sharpens his eyes on me."
    },
    {
      "n": 10,
      "t": "They have gaped on me with their mouth; they have smitten me on the cheek reproachfully; they have gathered themselves together against me."
    },
    {
      "n": 11,
      "t": "God has delivered me to the ungodly, and turned me over into the hands of the wicked."
    },
    {
      "n": 12,
      "t": "I was at ease, but he has broken me asunder: he has also taken me by my neck, and shaken me to pieces, and set me up for his mark."
    },
    {
      "n": 13,
      "t": "His archers compass me round about, he splits my reins asunder, and does not spare; he pours out my gall on the ground."
    },
    {
      "n": 14,
      "t": "He breaks me with breach on breach, he runs on me like a giant."
    },
    {
      "n": 15,
      "t": "I have sewed sackcloth on my skin, and defiled my horn in the dust."
    },
    {
      "n": 16,
      "t": "My face is foul with weeping, and on my eyelids is the shadow of death;"
    },
    {
      "n": 17,
      "t": "Not for any injustice in my hands: also my prayer is pure."
    },
    {
      "n": 18,
      "t": "O earth, cover not you my blood, and let my cry have no place."
    },
    {
      "n": 19,
      "t": "Also now, behold, my witness is in heaven, and my record is on high."
    },
    {
      "n": 20,
      "t": "My friends scorn me: but my eye pours out tears to God."
    },
    {
      "n": 21,
      "t": "O that one might plead for a man with God, as a man pleads for his neighbor!"
    },
    {
      "n": 22,
      "t": "When a few years are come, then I shall go the way from where I shall not return."
    }
  ]
}
