{
  "book": "job",
  "bookName": "Job",
  "testament": "OT",
  "chapter": 20,
  "totalChapters": 42,
  "verses": [
    {
      "n": 1,
      "t": "Then Sophar the Minæan answered and said,"
    },
    {
      "n": 2,
      "t": "I did not suppose that thou wouldest answer thus: neither do ye understand more than I."
    },
    {
      "n": 3,
      "t": "I will hear my shameful reproach; and the spirit of my understanding answers me."
    },
    {
      "n": 4,
      "t": "Hast thou [not] known these things of old, from the time that man was set upon the earth?"
    },
    {
      "n": 5,
      "t": "But the mirth of the ungodly is a signal downfall, and the joy of transgressors is destruction:"
    },
    {
      "n": 6,
      "t": "although his gifts should go up to heaven, and his sacrifice reach the clouds."
    },
    {
      "n": 7,
      "t": "For when he shall seem to be now established, then he shall utterly perish: and they that knew him shall say, Where is he?"
    },
    {
      "n": 8,
      "t": "Like a dream that has fled away, he shall not be found; and he has fled like a vision of the night."
    },
    {
      "n": 9,
      "t": "The eye has looked upon him, but shall not [see him] again; and his place shall no longer perceive him."
    },
    {
      "n": 10,
      "t": "Let [his] inferiors destroy his children, and let his hands kindle the fire of sorrow."
    },
    {
      "n": 11,
      "t": "His bones have been filled with [vigour of] his youth, and it shall lie down with him in the dust."
    },
    {
      "n": 12,
      "t": "Though evil be sweet in his mouth, [though] he will hide it under his tongue;"
    },
    {
      "n": 13,
      "t": "though he will not spare it, and will not leave it, but will keep it in the midst of his throat:"
    },
    {
      "n": 14,
      "t": "yet he shall not at all be able to help himself; the gall of an asp is in his belly."
    },
    {
      "n": 15,
      "t": "[His] wealth unjustly collected shall be vomited up; a messenger [of wrath] shall drag him out of his house."
    },
    {
      "n": 16,
      "t": "And let him suck the poison of serpents, and let the serpent's tongue slay him."
    },
    {
      "n": 17,
      "t": "Let him not see the milk of the pastures, nor the supplies of honey and butter."
    },
    {
      "n": 18,
      "t": "He has laboured unprofitably and in vain, [for] wealth of which he shall not taste: [it is] as a lean thing, unfit for food, which he cannot swallow."
    },
    {
      "n": 19,
      "t": "For he has broken down the houses of many mighty men: and he has plundered an habitation, though he built [it] not."
    },
    {
      "n": 20,
      "t": "There is no security to his possessions; he shall not be saved by his desire."
    },
    {
      "n": 21,
      "t": "There is nothing remaining of his provisions; therefore his goods shall not flourish."
    },
    {
      "n": 22,
      "t": "But when he shall seem to be just satisfied, he shall be straitened; and all distress shall come upon him."
    },
    {
      "n": 23,
      "t": "If by any means he would fill his belly, let [God] send upon him the fury of wrath; let him bring a torrent of pains upon him."
    },
    {
      "n": 24,
      "t": "And he shall by no means escape from the power of the sword; let the brazen bow wound him."
    },
    {
      "n": 25,
      "t": "And let the arrow pierce through his body; and let the stars be against his dwelling-place: let terrors come upon him."
    },
    {
      "n": 26,
      "t": "And let all darkness wait for him: a fire that burns not out shall consume him; and let a stranger plague his house."
    },
    {
      "n": 27,
      "t": "And let the heaven reveal his iniquities, and the earth rise up against him."
    },
    {
      "n": 28,
      "t": "Let destruction bring his house to an end; let a day of wrath come upon him."
    },
    {
      "n": 29,
      "t": "This is the portion of an ungodly man from the Lord, and the possession of his goods [appointed him] by the all-seeing [God]."
    }
  ]
}
